gym_d2d/__init__.py
gym_d2d/action.py
gym_d2d/channel.py
gym_d2d/conversion.py
gym_d2d/device.py
gym_d2d/id.py
gym_d2d/link_type.py
gym_d2d/path_loss.py
gym_d2d/position.py
gym_d2d/simulator.py
gym_d2d/traffic_model.py
gym_d2d/utils.py
gym_d2d/envs/__init__.py
gym_d2d/envs/d2d_env.py
gym_d2d/envs/devices.py
gym_d2d/envs/env_config.py
gym_d2d/envs/obs_fn.py
gym_d2d/envs/reward_fn.py
gym_d2d-0.0.3.dist-info/LICENSE.txt
gym_d2d-0.0.3.dist-info/METADATA
gym_d2d-0.0.3.dist-info/WHEEL
gym_d2d-0.0.3.dist-info/top_level.txt
gym_d2d-0.0.3.dist-info/RECORD
