Metadata-Version: 2.1
Name: gym-d2d
Version: 0.0.3
Summary: Device-to-Device (D2D) communication OpenAI Gym environment
Home-page: https://github.com/davidcotton/gym-d2d
License: UNKNOWN
Keywords: open ai gym environment rl agent d2d cellular offload resource allocation
Platform: UNKNOWN
Requires-Dist: gym (>=0.9.6)
Requires-Dist: numpy
Provides-Extra: dev
Requires-Dist: flake8 ; extra == 'dev'
Requires-Dist: pytest ; extra == 'dev'
Requires-Dist: pytest-cov ; extra == 'dev'
Requires-Dist: pytest-sugar ; extra == 'dev'
